{
  "_id": "C23NYv8K71muiLo1",
  "name": "Sleight of Hand",
  "type": "feat",
  "img": "icons/sundries/books/book-purple-cross.webp",
  "effects": [],
  "folder": "AavGVqmE65s8lAG5",
  "flags": {},
  "system": {
    "description": {
      "gm": "",
      "value": "<p>You are able to appear as if you are performing one action while in actuality you are doing another, by making use of the illusion granted through your Noble Mask. You gain the Sleight of Hand focus spell.</p>"
    },
    "rules": [],
    "slug": "sleight-of-hand",
    "_migration": {
      "version": 0.935,
      "lastMigration": null,
      "previous": {
        "schema": 0.934,
        "foundry": "12.331",
        "system": "6.7.2"
      }
    },
    "traits": {
      "otherTags": [],
      "value": [
        "archetype"
      ],
      "rarity": "uncommon"
    },
    "publication": {
      "title": "Immortal Ardor",
      "authors": "Sammy Rachman",
      "license": "OGL",
      "remaster": true
    },
    "level": {
      "value": 2
    },
    "category": "class",
    "onlyLevel1": false,
    "maxTakable": 1,
    "actionType": {
      "value": "passive"
    },
    "actions": {
      "value": null
    },
    "prerequisites": {
      "value": [
        {
          "value": "Courtier Dedication"
        }
      ]
    },
    "location": null,
    "subfeatures": {
      "proficiencies": {},
      "senses": {},
      "suppressedFeatures": []
    }
  },
  "_stats": {
    "compendiumSource": "Compendium.forge-vtt-shared-compendiums-seekers-data.item-1-seekers-items.Item.C23NYv8K71muiLo1",
    "duplicateSource": null,
    "coreVersion": "13.347",
    "systemId": "pf2e",
    "systemVersion": "6.9.0",
    "exportSource": null
  },
  "sort": 0,
  "ownership": {
    "default": 0,
    "MDg2MGU5NzgyN2Nh": 3,
    "xrtJn5KNHicBTyJb": 3
  },
  "_key": "!items!C23NYv8K71muiLo1"
}
