{
  "folder": "YN98XSz3i0bXGAwA",
  "name": "Legendary Spellcaster",
  "type": "feat",
  "effects": [],
  "system": {
    "description": {
      "gm": "",
      "value": "<p><span lang=\"EN\">Your skill in identifying and experimenting with the distant limits of magic through spellcraft is unparalleled. You become Legendary in spell attacks and spell DCs.</span></p>"
    },
    "rules": [],
    "slug": "legendary-spellcaster",
    "_migration": {
      "version": 0.955,
      "previous": {
        "schema": 0.953,
        "foundry": "13.351",
        "system": "7.10.1"
      }
    },
    "traits": {
      "otherTags": [],
      "value": [
        "luminary"
      ],
      "rarity": "common"
    },
    "publication": {
      "title": "Immortal Ardor",
      "authors": "Sammy Rachman",
      "license": "OGL",
      "remaster": true
    },
    "level": {
      "value": 19
    },
    "category": "classfeature",
    "onlyLevel1": false,
    "maxTakable": 1,
    "actionType": {
      "value": "passive"
    },
    "actions": {
      "value": null
    },
    "prerequisites": {
      "value": []
    },
    "location": null,
    "subfeatures": {
      "proficiencies": {
        "spellcasting": {
          "rank": 4,
          "attribute": null
        }
      },
      "senses": {},
      "suppressedFeatures": []
    }
  },
  "img": "icons/sundries/books/book-open-purple.webp",
  "ownership": {
    "default": 0,
    "xrtJn5KNHicBTyJb": 3
  },
  "flags": {},
  "_stats": {
    "compendiumSource": null,
    "duplicateSource": null,
    "exportSource": null,
    "coreVersion": "13.351",
    "systemId": "pf2e",
    "systemVersion": "7.10.1"
  },
  "_id": "k3ilvTgwXxCaJA5E",
  "sort": 0,
  "_key": "!items!k3ilvTgwXxCaJA5E"
}
